licenseme_cli/__init__.py
licenseme_cli/__main__.py
licenseme_cli/cli.py
licenseme_cli/data/licenses/AGPL-3.0-only.txt
licenseme_cli/data/licenses/AGPL-3.0-or-later.txt
licenseme_cli/data/licenses/Apache-2.0.txt
licenseme_cli/data/licenses/BSD-2-Clause.txt
licenseme_cli/data/licenses/BSD-3-Clause.txt
licenseme_cli/data/licenses/BSL-1.0.txt
licenseme_cli/data/licenses/CC0-1.0.txt
licenseme_cli/data/licenses/EPL-2.0.txt
licenseme_cli/data/licenses/GPL-2.0-only.txt
licenseme_cli/data/licenses/GPL-2.0-or-later.txt
licenseme_cli/data/licenses/GPL-3.0-only.txt
licenseme_cli/data/licenses/GPL-3.0-or-later.txt
licenseme_cli/data/licenses/ISC.txt
licenseme_cli/data/licenses/LGPL-2.1-only.txt
licenseme_cli/data/licenses/LGPL-2.1-or-later.txt
licenseme_cli/data/licenses/LGPL-3.0-or-later.txt
licenseme_cli/data/licenses/MIT.txt
licenseme_cli/data/licenses/MPL-2.0.txt
licenseme_cli/data/licenses/Unlicense.txt
licenseme_cli/data/licenses/WTFPL.txt
licenseme_cli-0.1.0.dist-info/licenses/LICENSE
licenseme_cli-0.1.0.dist-info/METADATA
licenseme_cli-0.1.0.dist-info/WHEEL
licenseme_cli-0.1.0.dist-info/entry_points.txt
licenseme_cli-0.1.0.dist-info/top_level.txt
licenseme_cli-0.1.0.dist-info/RECORD
