Metadata-Version: 2.4
Name: licenseme-cli
Version: 0.1.0
Summary: Interactive SPDX-based license generator
Home-page: https://github.com/tcsenpai/licenseme
Author: tcsenpai
Author-email: tcsenpai <tcsenpai@discus.sh>
License: MIT License
Project-URL: Homepage, https://github.com/tcsenpai/licenseme
Project-URL: Source, https://github.com/tcsenpai/licenseme
Keywords: license,spdx,cli
Classifier: Programming Language :: Python :: 3
Classifier: License :: OSI Approved :: MIT License
Classifier: Topic :: Software Development :: Build Tools
Requires-Python: >=3.9
License-File: LICENSE
Dynamic: license-file
